regorus/regorus.pyi
regorus/regorus.abi3.so
regorus/py.typed
regorus/__init__.py
celine_regorus-0.9.0.dist-info/WHEEL
celine_regorus-0.9.0.dist-info/METADATA
celine_regorus-0.9.0.dist-info/RECORD
